<?xml version="1.0" encoding="utf-8"?>
<ImportExportXml version="9.2.23104.240" SolutionPackageVersion="9.2" languagecode="1033" generatedBy="CrmLive" xmlns:xsi="http://www.w3.org/2001/XMLSchema-instance">
  <SolutionManifest>
    <UniqueName>TimesheetEntities</UniqueName>
    <LocalizedNames>
      <LocalizedName description="Timesheet Entities" languagecode="1033" />
    </LocalizedNames>
    <Descriptions />
    <Version>1.0.0.0</Version>
    <Managed>0</Managed>
    <Publisher>
      <UniqueName>barikada</UniqueName>
      <LocalizedNames>
        <LocalizedName description="Barikada OOD" languagecode="1033" />
      </LocalizedNames>
      <Descriptions />
      <EMailAddress xsi:nil="true"></EMailAddress>
      <SupportingWebsiteUrl xsi:nil="true"></SupportingWebsiteUrl>
      <CustomizationPrefix>bar</CustomizationPrefix>
      <CustomizationOptionValuePrefix>75523</CustomizationOptionValuePrefix>
      <Addresses>
        <Address>
          <AddressNumber>1</AddressNumber>
          <AddressTypeCode>1</AddressTypeCode>
          <City xsi:nil="true"></City>
          <County xsi:nil="true"></County>
          <Country xsi:nil="true"></Country>
          <Fax xsi:nil="true"></Fax>
          <FreightTermsCode xsi:nil="true"></FreightTermsCode>
          <ImportSequenceNumber xsi:nil="true"></ImportSequenceNumber>
          <Latitude xsi:nil="true"></Latitude>
          <Line1 xsi:nil="true"></Line1>
          <Line2 xsi:nil="true"></Line2>
          <Line3 xsi:nil="true"></Line3>
          <Longitude xsi:nil="true"></Longitude>
          <Name xsi:nil="true"></Name>
          <PostalCode xsi:nil="true"></PostalCode>
          <PostOfficeBox xsi:nil="true"></PostOfficeBox>
          <PrimaryContactName xsi:nil="true"></PrimaryContactName>
          <ShippingMethodCode>1</ShippingMethodCode>
          <StateOrProvince xsi:nil="true"></StateOrProvince>
          <Telephone1 xsi:nil="true"></Telephone1>
          <Telephone2 xsi:nil="true"></Telephone2>
          <Telephone3 xsi:nil="true"></Telephone3>
          <TimeZoneRuleVersionNumber xsi:nil="true"></TimeZoneRuleVersionNumber>
          <UPSZone xsi:nil="true"></UPSZone>
          <UTCOffset xsi:nil="true"></UTCOffset>
          <UTCConversionTimeZoneCode xsi:nil="true"></UTCConversionTimeZoneCode>
        </Address>
        <Address>
          <AddressNumber>2</AddressNumber>
          <AddressTypeCode>1</AddressTypeCode>
          <City xsi:nil="true"></City>
          <County xsi:nil="true"></County>
          <Country xsi:nil="true"></Country>
          <Fax xsi:nil="true"></Fax>
          <FreightTermsCode xsi:nil="true"></FreightTermsCode>
          <ImportSequenceNumber xsi:nil="true"></ImportSequenceNumber>
          <Latitude xsi:nil="true"></Latitude>
          <Line1 xsi:nil="true"></Line1>
          <Line2 xsi:nil="true"></Line2>
          <Line3 xsi:nil="true"></Line3>
          <Longitude xsi:nil="true"></Longitude>
          <Name xsi:nil="true"></Name>
          <PostalCode xsi:nil="true"></PostalCode>
          <PostOfficeBox xsi:nil="true"></PostOfficeBox>
          <PrimaryContactName xsi:nil="true"></PrimaryContactName>
          <ShippingMethodCode>1</ShippingMethodCode>
          <StateOrProvince xsi:nil="true"></StateOrProvince>
          <Telephone1 xsi:nil="true"></Telephone1>
          <Telephone2 xsi:nil="true"></Telephone2>
          <Telephone3 xsi:nil="true"></Telephone3>
          <TimeZoneRuleVersionNumber xsi:nil="true"></TimeZoneRuleVersionNumber>
          <UPSZone xsi:nil="true"></UPSZone>
          <UTCOffset xsi:nil="true"></UTCOffset>
          <UTCConversionTimeZoneCode xsi:nil="true"></UTCConversionTimeZoneCode>
        </Address>
      </Addresses>
    </Publisher>
    <RootComponents>
      <RootComponent type="1" schemaName="bar_billto" behavior="0" />
      <RootComponent type="1" schemaName="bar_timeentries" behavior="0" />
      <RootComponent type="183" id="{1266332f-61f3-ed11-8849-000d3ab9e893}" schemaName="VCP_DS_4d4b54e2-3fca-44dc-ab1e-37b7152d6c2d" behavior="0" />
    </RootComponents>
    <MissingDependencies>
      <MissingDependency>
        <Required type="181" schemaName="Virtual Connector Data Provider" displayName="Virtual Connector Data Provider" solution="msft_ConnectorProvider (9.0.0.1411)" id="{b581d5dc-72e1-ea11-a81e-000d3af5fff1}">
          <package>msft_ConnectorProviderAnchor (9.0.0.1411)</package>
        </Required>
        <Dependent type="1" schemaName="bar_billto" displayName="BillTo" />
      </MissingDependency>
      <MissingDependency>
        <Required type="181" schemaName="Virtual Connector Data Provider" displayName="Virtual Connector Data Provider" solution="msft_ConnectorProvider (9.0.0.1411)" id="{b581d5dc-72e1-ea11-a81e-000d3af5fff1}">
          <package>msft_ConnectorProviderAnchor (9.0.0.1411)</package>
        </Required>
        <Dependent type="1" schemaName="bar_timeentries" displayName="TimeEntries" />
      </MissingDependency>
      <MissingDependency>
        <Required type="181" schemaName="Virtual Connector Data Provider" displayName="Virtual Connector Data Provider" solution="msft_ConnectorProvider (9.0.0.1411)" id="{b581d5dc-72e1-ea11-a81e-000d3af5fff1}">
          <package>msft_ConnectorProviderAnchor (9.0.0.1411)</package>
        </Required>
        <Dependent type="183" schemaName="VCP_DS_4d4b54e2-3fca-44dc-ab1e-37b7152d6c2d" displayName="VCP_DS_4d4b54e2-3fca-44dc-ab1e-37b7152d6c2d" id="{1266332f-61f3-ed11-8849-000d3ab9e893}" />
      </MissingDependency>
    </MissingDependencies>
  </SolutionManifest>
</ImportExportXml>